{".class": "MypyFile", "_fullname": "restfull_tvshows_app.views", "is_partial_stub_package": false, "is_stub": false, "names": {".class": "SymbolTable", "Show": {".class": "SymbolTableNode", "cross_ref": "restfull_tvshows_app.models.Show", "kind": "Gdef"}, "__doc__": {".class": "SymbolTableNode", "kind": "Gdef", "node": {".class": "Var", "flags": ["is_ready"], "fullname": "restfull_tvshows_app.views.__doc__", "name": "__doc__", "type": "builtins.str"}}, "__file__": {".class": "SymbolTableNode", "kind": "Gdef", "node": {".class": "Var", "flags": ["is_ready"], "fullname": "restfull_tvshows_app.views.__file__", "name": "__file__", "type": "builtins.str"}}, "__name__": {".class": "SymbolTableNode", "kind": "Gdef", "node": {".class": "Var", "flags": ["is_ready"], "fullname": "restfull_tvshows_app.views.__name__", "name": "__name__", "type": "builtins.str"}}, "__package__": {".class": "SymbolTableNode", "kind": "Gdef", "node": {".class": "Var", "flags": ["is_ready"], "fullname": "restfull_tvshows_app.views.__package__", "name": "__package__", "type": "builtins.str"}}, "create_show": {".class": "SymbolTableNode", "kind": "Gdef", "node": {".class": "FuncDef", "arg_kinds": [0], "arg_names": ["request"], "flags": [], "fullname": "restfull_tvshows_app.views.create_show", "name": "create_show", "type": null}}, "delete_tvshow": {".class": "SymbolTableNode", "kind": "Gdef", "node": {".class": "FuncDef", "arg_kinds": [0], "arg_names": ["request"], "flags": [], "fullname": "restfull_tvshows_app.views.delete_tvshow", "name": "delete_tvshow", "type": null}}, "edit_tvshow": {".class": "SymbolTableNode", "kind": "Gdef", "node": {".class": "FuncDef", "arg_kinds": [0], "arg_names": ["request"], "flags": [], "fullname": "restfull_tvshows_app.views.edit_tvshow", "name": "edit_tvshow", "type": null}}, "index": {".class": "SymbolTableNode", "kind": "Gdef", "node": {".class": "FuncDef", "arg_kinds": [0], "arg_names": ["request"], "flags": [], "fullname": "restfull_tvshows_app.views.index", "name": "index", "type": null}}, "redirect": {".class": "SymbolTableNode", "kind": "Gdef", "node": {".class": "Var", "flags": ["is_suppressed_import", "is_ready"], "fullname": "restfull_tvshows_app.views.redirect", "name": "redirect", "type": {".class": "AnyType", "missing_import_name": "restfull_tvshows_app.views.redirect", "source_any": null, "type_of_any": 3}}}, "render": {".class": "SymbolTableNode", "kind": "Gdef", "node": {".class": "Var", "flags": ["is_suppressed_import", "is_ready"], "fullname": "restfull_tvshows_app.views.render", "name": "render", "type": {".class": "AnyType", "missing_import_name": "restfull_tvshows_app.views.render", "source_any": null, "type_of_any": 3}}}, "show_this_show": {".class": "SymbolTableNode", "kind": "Gdef", "node": {".class": "FuncDef", "arg_kinds": [0, 0], "arg_names": ["request", "id"], "flags": [], "fullname": "restfull_tvshows_app.views.show_this_show", "name": "show_this_show", "type": null}}, "shows_new": {".class": "SymbolTableNode", "kind": "Gdef", "node": {".class": "FuncDef", "arg_kinds": [0], "arg_names": ["request"], "flags": [], "fullname": "restfull_tvshows_app.views.shows_new", "name": "shows_new", "type": null}}}, "path": "/Users/zionhugh/GoogleDrive_Folder/Code_Practices/CodingDojo/python_stack/django/django_intro/assignment/semi_restful_tv_shows/restfull_tvshows_proj/restfull_tvshows_app/views.py"}