{"id": "favorite_book_app.models", "path": "/Users/zionhugh/GoogleDrive_Folder/Code_Practices/CodingDojo/python_stack/django/django_intro/assignment/FavoriteBooks/server/favorite_book_app/models.py", "mtime": 1576094590, "size": 1539, "hash": "99afb3a63defbf9adbf22694213d653a", "data_mtime": 1576093756, "dependencies": ["re", "builtins", "abc", "enum", "typing"], "suppressed": ["django.db"], "child_modules": [], "options": {"disallow_untyped_calls": false, "follow_imports_for_stubs": false, "disallow_any_generics": false, "disallow_any_explicit": false, "disallow_any_decorated": false, "always_false": [], "warn_unreachable": false, "implicit_reexport": true, "disallow_untyped_decorators": false, "mypyc": false, "bazel": false, "disallow_any_expr": false, "show_none_errors": true, "disallow_incomplete_defs": false, "warn_return_any": false, "warn_no_return": true, "strict_optional": true, "always_true": [], "plugins": [], "allow_untyped_globals": false, "disallow_untyped_defs": false, "strict_equality": false, "allow_redefinition": false, "ignore_missing_imports": true, "no_implicit_optional": false, "ignore_errors": false, "strict_optional_whitelist": null, "disallow_subclassing_any": false, "follow_imports": "silent", "warn_unused_ignores": false, "disallow_any_unimported": false, "local_partial_types": false, "check_untyped_defs": false, "platform": "darwin"}, "dep_prios": [10, 5, 30, 30, 30, 5], "dep_lines": [2, 1, 1, 1, 1, 1], "interface_hash": "d39467cee5674ea8d2e83b542ac36bda", "version_id": "0.750", "ignore_all": false, "plugin_data": null}